{
  "$schema": "https://developer.microsoft.com/json-schemas/fabric/item/report/definition/visualContainer/2.6.0/schema.json",
  "name": "a9b6a8d850dda08a799d",
  "position": {
    "x": 28.263219633369371,
    "y": 173.34774708466546,
    "z": 4000,
    "height": 535.11695839179333,
    "width": 612.369758723003,
    "tabOrder": 4000
  },
  "visual": {
    "visualType": "areaChart",
    "query": {
      "queryState": {
        "Category": {
          "projections": [
            {
              "field": {
                "Column": {
                  "Expression": {
                    "SourceRef": {
                      "Entity": "DateHourBridge"
                    }
                  },
                  "Property": "Hour"
                }
              },
              "queryRef": "DateHourBridge.Hour",
              "nativeQueryRef": "Hour",
              "active": true
            }
          ]
        },
        "Y": {
          "projections": [
            {
              "field": {
                "Aggregation": {
                  "Expression": {
                    "Column": {
                      "Expression": {
                        "SourceRef": {
                          "Entity": "smartcity_environment_weather_traffic_forecastnext6hours_ml_historical_current"
                        }
                      },
                      "Property": "Predicted_AvgSpeed_kmph"
                    }
                  },
                  "Function": 1
                }
              },
              "queryRef": "Avg(smartcity_environment_weather_traffic_forecastnext6hours_ml_historical_current.Predicted_AvgSpeed_kmph)",
              "nativeQueryRef": "Average of Predicted_AvgSpeed_kmph"
            }
          ]
        }
      },
      "sortDefinition": {
        "sort": [
          {
            "field": {
              "Column": {
                "Expression": {
                  "SourceRef": {
                    "Entity": "DateHourBridge"
                  }
                },
                "Property": "Hour"
              }
            },
            "direction": "Ascending"
          }
        ],
        "isDefaultSort": true
      }
    },
    "objects": {
      "zoom": [
        {
          "properties": {
            "show": {
              "expr": {
                "Literal": {
                  "Value": "true"
                }
              }
            }
          }
        }
      ]
    },
    "drillFilterOtherVisuals": true
  }
}